{
	"animations": [
		{
			"offsets": [
				142,
				-68
			],
			"loop": false,
			"fps": 24,
			"anim": "singLEFT",
			"indices": [],
			"name": "left"
		},
		{
			"offsets": [
				30,
				-73
			],
			"loop": false,
			"fps": 24,
			"anim": "singDOWN",
			"indices": [],
			"name": "down"
		},
		{
			"offsets": [
				12,
				80
			],
			"loop": false,
			"fps": 24,
			"anim": "singUP",
			"indices": [],
			"name": "up"
		},
		{
			"offsets": [
				10,
				0
			],
			"loop": false,
			"fps": 24,
			"anim": "singRIGHT",
			"indices": [],
			"name": "right"
		},
		{
			"offsets": [
				0,
				0
			],
			"loop": true,
			"fps": 24,
			"anim": "idle",
			"indices": [],
			"name": "idle"
		}
	],
	"no_antialiasing": false,
	"image": "characters/chotix",
	"position": [
		90,
		250
	],
	"healthicon": "chotix",
	"flip_x": false,
	"healthbar_colors": [
		251,
		87,
		116
	],
	"camera_position": [
		-50,
		-60
	],
	"sing_duration": 6.1,
	"scale": 1.35
}